nominal_api_protos/nominal_write_pb2.py
nominal_api_protos/nominal_write_pb2.pyi
nominal_api_protos/nominal_write_pb2_grpc.py
nominal_api_protos/prometheus_remote_write_pb2.py
nominal_api_protos/prometheus_remote_write_pb2.pyi
nominal_api_protos/prometheus_remote_write_pb2_grpc.py
nominal_api_protos/py.typed
nominal_api_protos/nominal/ai/v1/ai_agent_pb2.py
nominal_api_protos/nominal/ai/v1/ai_agent_pb2.pyi
nominal_api_protos/nominal/ai/v1/ai_agent_pb2_grpc.py
nominal_api_protos/nominal/ai/v1/knowledge_base_pb2.py
nominal_api_protos/nominal/ai/v1/knowledge_base_pb2.pyi
nominal_api_protos/nominal/ai/v1/knowledge_base_pb2_grpc.py
nominal_api_protos/nominal/ai/v1/model_provider_health_pb2.py
nominal_api_protos/nominal/ai/v1/model_provider_health_pb2.pyi
nominal_api_protos/nominal/ai/v1/model_provider_health_pb2_grpc.py
nominal_api_protos/nominal/application/v1/application_pb2.py
nominal_api_protos/nominal/application/v1/application_pb2.pyi
nominal_api_protos/nominal/application/v1/application_pb2_grpc.py
nominal_api_protos/nominal/authentication/groups/v1/groups_pb2.py
nominal_api_protos/nominal/authentication/groups/v1/groups_pb2.pyi
nominal_api_protos/nominal/authentication/groups/v1/groups_pb2_grpc.py
nominal_api_protos/nominal/authorization/markings/v1/markings_pb2.py
nominal_api_protos/nominal/authorization/markings/v1/markings_pb2.pyi
nominal_api_protos/nominal/authorization/markings/v1/markings_pb2_grpc.py
nominal_api_protos/nominal/authorization/permissions/v1/permissions_pb2.py
nominal_api_protos/nominal/authorization/permissions/v1/permissions_pb2.pyi
nominal_api_protos/nominal/authorization/permissions/v1/permissions_pb2_grpc.py
nominal_api_protos/nominal/authorization/roles/v1/roles_pb2.py
nominal_api_protos/nominal/authorization/roles/v1/roles_pb2.pyi
nominal_api_protos/nominal/authorization/roles/v1/roles_pb2_grpc.py
nominal_api_protos/nominal/blob_storage_service/v1/blob_storage_service_pb2.py
nominal_api_protos-0.1099.0.dist-info/METADATA
nominal_api_protos-0.1099.0.dist-info/WHEEL
nominal_api_protos-0.1099.0.dist-info/top_level.txt
nominal_api_protos-0.1099.0.dist-info/RECORD
