Metadata-Version: 2.4
Name: nominal-api-protos
Version: 0.1099.0
Requires-Python: >=3.8
Requires-Dist: protobuf>=5.25.0
Requires-Dist: grpcio>=1.76.0
Requires-Dist: grpcio-tools>=1.76.0
Dynamic: requires-dist
Dynamic: requires-python
